README.rst
setup.cfg
setup.py
fab_geoalchemy/__init__.py
fab_geoalchemy/fields.py
fab_geoalchemy/interface.py
fab_geoalchemy/version.py
fab_geoalchemy/views.py
fab_geoalchemy/widgets.py
fab_geoalchemy.egg-info/PKG-INFO
fab_geoalchemy.egg-info/SOURCES.txt
fab_geoalchemy.egg-info/dependency_links.txt
fab_geoalchemy.egg-info/requires.txt
fab_geoalchemy.egg-info/top_level.txt