Metadata-Version: 2.1
Name: fab-geoalchemy
Version: 0.1.4
Summary: Plugin to implement Geoalchemy fields in Flask Appbuilder
Home-page: https://github.com/dolfandringa/fab_geoalchemy
Author: Dolf Andringa
Author-email: dolfandringa@gmail.com
License: UNKNOWN
Project-URL: Source, https://github.com/dolfandringa/fab_geoalchemy/
Keywords: gis sqlalchemy
Platform: UNKNOWN
Classifier: Programming Language :: Python :: 3
Classifier: Development Status :: 3 - Alpha
Classifier: Topic :: Scientific/Engineering :: GIS
Classifier: Topic :: Database :: Front-Ends
Classifier: License :: OSI Approved :: MIT License
Provides-Extra: test
